django_singlestore/__init__.py
django_singlestore/base.py
django_singlestore/client.py
django_singlestore/compiler.py
django_singlestore/creation.py
django_singlestore/features.py
django_singlestore/functions.py
django_singlestore/introspection.py
django_singlestore/operations.py
django_singlestore/schema.py
django_singlestore/utils.py
django_singlestore/validation.py
django_singlestore-5.0.1.dist-info/licenses/LICENSE
django_singlestore-5.0.1.dist-info/METADATA
django_singlestore-5.0.1.dist-info/WHEEL
django_singlestore-5.0.1.dist-info/top_level.txt
django_singlestore-5.0.1.dist-info/RECORD
