Metadata-Version: 2.4
Name: django_singlestore
Version: 5.0.1
Summary: Django backend for SingleStore
Home-page: https://github.com/singlestore-labs/django-singlestore
Maintainer: SingleStore Inc.
Maintainer-email: support@singlestore.com
License: BSD-3-Clause
Project-URL: Source, https://github.com/singlestore-labs/django-singlestore
Project-URL: Tracker, https://github.com/singlestore-labs/django-singlestore/issues
Classifier: Development Status :: 4 - Beta
Classifier: Framework :: Django
Classifier: License :: OSI Approved :: BSD License
Classifier: Operating System :: OS Independent
Classifier: Programming Language :: Python
Classifier: Programming Language :: Python :: 3
Classifier: Programming Language :: Python :: 3 :: Only
Requires-Python: >=3.9
License-File: LICENSE
Requires-Dist: django>=5.0
Requires-Dist: singlestoredb>=1.12.4
Dynamic: license-file
